metadata_guardian-0.3.0.dist-info/METADATA
metadata_guardian-0.3.0.dist-info/WHEEL
metadata_guardian-0.3.0.dist-info/entry_points.txt
metadata_guardian-0.3.0.dist-info/licenses/LICENSE.txt
metadata_guardian/report.py
metadata_guardian/rules/inclusion_rules.yaml
metadata_guardian/rules/__init__.py
metadata_guardian/rules/pii_rules.yaml
metadata_guardian/scanner.py
metadata_guardian/source/external/kafka_schema_registry_source.py
metadata_guardian/source/external/gcp_source.py
metadata_guardian/source/external/aws_source.py
metadata_guardian/source/external/deltatable_source.py
metadata_guardian/source/external/mysql_source.py
metadata_guardian/source/external/snowflake_source.py
metadata_guardian/source/external/external_metadata_source.py
metadata_guardian/source/external/__init__.py
metadata_guardian/source/metadata_source.py
metadata_guardian/source/local/avro_source.py
metadata_guardian/source/local/orc_source.py
metadata_guardian/source/local/__init__.py
metadata_guardian/source/local/avro_schema_source.py
metadata_guardian/source/local/local_metadata_source.py
metadata_guardian/source/local/parquet_source.py
metadata_guardian/source/__init__.py
metadata_guardian/exceptions.py
metadata_guardian/__init__.py
metadata_guardian/cli/external/__init__.py
metadata_guardian/cli/local/__init__.py
metadata_guardian/cli/__init__.py
metadata_guardian/cli/__main__.py
metadata_guardian/conf.py
metadata_guardian/data_rules.py
metadata_guardian/py.typed
metadata_guardian/metadata_guardian.abi3.so
metadata_guardian-0.3.0.dist-info/RECORD
