Metadata-Version: 2.4
Name: metadata_guardian
Version: 0.3.0
Classifier: Development Status :: 3 - Alpha
Classifier: License :: OSI Approved :: Apache Software License
Classifier: Programming Language :: Python :: 3 :: Only
Requires-Dist: rich
Requires-Dist: loguru
Requires-Dist: pyarrow
Requires-Dist: typer
Requires-Dist: pydantic
Requires-Dist: avro ; extra == 'all'
Requires-Dist: snowflake-connector-python ; extra == 'all'
Requires-Dist: boto3 ; extra == 'all'
Requires-Dist: boto3-stubs[athena,glue] ; extra == 'all'
Requires-Dist: deltalake ; extra == 'all'
Requires-Dist: google-cloud-bigquery ; extra == 'all'
Requires-Dist: confluent-kafka[schemaregistry] ; extra == 'all'
Requires-Dist: pymysql ; extra == 'all'
Requires-Dist: types-pymysql ; extra == 'all'
Requires-Dist: pandas ; extra == 'all'
Requires-Dist: snowflake-connector-python ; extra == 'snowflake'
Requires-Dist: avro ; extra == 'avro'
Requires-Dist: boto3 ; extra == 'aws'
Requires-Dist: boto3-stubs[athena,glue] ; extra == 'aws'
Requires-Dist: google-cloud-bigquery ; extra == 'gcp'
Requires-Dist: deltalake ; extra == 'deltalake'
Requires-Dist: pandas ; extra == 'deltalake'
Requires-Dist: confluent-kafka ; extra == 'kafka_schema_registry'
Requires-Dist: pymysql ; extra == 'mysql'
Requires-Dist: types-pymysql ; extra == 'mysql'
Requires-Dist: mypy ; extra == 'devel'
Requires-Dist: black ; extra == 'devel'
Requires-Dist: isort ; extra == 'devel'
Requires-Dist: pytest ; extra == 'devel'
Requires-Dist: pytest-mock ; extra == 'devel'
Requires-Dist: pytest-cov ; extra == 'devel'
Requires-Dist: pytest-xdist ; extra == 'devel'
Requires-Dist: pytest-clarity ; extra == 'devel'
Requires-Dist: sphinx ; extra == 'devel'
Requires-Dist: pydata-sphinx-theme ; extra == 'devel'
Requires-Dist: toml ; extra == 'devel'
Requires-Dist: autodoc-pydantic ; extra == 'devel'
Provides-Extra: all
Provides-Extra: snowflake
Provides-Extra: avro
Provides-Extra: aws
Provides-Extra: gcp
Provides-Extra: deltalake
Provides-Extra: kafka_schema_registry
Provides-Extra: mysql
Provides-Extra: devel
License-File: LICENSE.txt
Summary: MetadataGuardian is used to protect data by searching the source metadata.
Keywords: pii,metadata,guardian,data
Home-Page: https://fvaleye.github.io/metadata-guardian/python
Author: Florian Valeye <fvaleye@github.com>
Author-email: Florian Valeye <fvaleye@github.com>
License: Apache-2.0
Requires-Python: >=3.9
Project-URL: documentation, https://fvaleye.github.io/metadata-guardian/python/
Project-URL: repository, https://github.com/fvaleye/metadata-guardian
